MANIFEST.in
README.md
setup.cfg
setup.py
./__init__.py
./attachment.py
./field.py
./tryton.cfg
./tests/__init__.py
./tests/test_view_and_depends.py
trytond_attachment_s3.egg-info/PKG-INFO
trytond_attachment_s3.egg-info/SOURCES.txt
trytond_attachment_s3.egg-info/dependency_links.txt
trytond_attachment_s3.egg-info/entry_points.txt
trytond_attachment_s3.egg-info/not-zip-safe
trytond_attachment_s3.egg-info/requires.txt
trytond_attachment_s3.egg-info/top_level.txt