Metadata-Version: 1.1
Name: trytond-attachment-s3
Version: 3.4.0.2
Summary: Amazon S3 backend for Tryton Attachments
Home-page: https://github.com/openlabs/trytond-attachment-s3
Author: Openlabs Technologies & Consulting (P) Limited
Author-email: UNKNOWN
License: BSD
Platform: UNKNOWN
Classifier: Development Status :: 5 - Production/Stable
Classifier: Environment :: No Input/Output (Daemon)
Classifier: Intended Audience :: Developers
Classifier: License :: OSI Approved :: BSD License
Classifier: Natural Language :: English
Classifier: Operating System :: OS Independent
Classifier: Programming Language :: Python :: 2.7
Classifier: Topic :: Software Development :: Libraries :: Application Frameworks
